synthetic_sample/__init__.py
synthetic_sample/calculation_utils.py
synthetic_sample/defaults.py
synthetic_sample/generate_synthetic_curves.py
synthetic_sample/generate_synthetic_records.py
synthetic_sample/sample_curve.py
synthetic_sample/synthetic_sample_generator.py
synthetic_sample-1.2.12.dist-info/METADATA
synthetic_sample-1.2.12.dist-info/WHEEL
synthetic_sample-1.2.12.dist-info/top_level.txt
synthetic_sample-1.2.12.dist-info/RECORD
