Metadata-Version: 2.1
Name: synthetic-sample
Version: 1.2.12
Summary: A generator for synthetic sales data
Home-page: https://github.com/amendmentai/synthetic_sample
Author: Makani Cartwright
Author-email: makani@amendmentai.com
Classifier: Programming Language :: Python :: 3
Classifier: Operating System :: OS Independent
Requires-Python: >=3.6
